shepard/__init__.py
shepard/cli.py
shepard/lib.py
shepard-1.0.2.dist-info/LICENSE
shepard-1.0.2.dist-info/METADATA
shepard-1.0.2.dist-info/WHEEL
shepard-1.0.2.dist-info/entry_points.txt
shepard-1.0.2.dist-info/top_level.txt
shepard-1.0.2.dist-info/RECORD
