Metadata-Version: 2.1
Name: shepard
Version: 1.0.2
Summary: Automating the creation of batch processing workflows in AWS!
Author-email: Shepard Team <shepard_dev_group@googlegroups.com>
Project-URL: Homepage, https://github.com/Jmevorach/New-Shepard
Project-URL: Bug Tracker, https://github.com/Jmevorach/New-Shepard/issues
Classifier: Programming Language :: Python :: 3
Classifier: License :: OSI Approved :: MIT License
License-File: LICENSE
Requires-Dist: click (==8.1.3)
Requires-Dist: boto3 (==1.26.89)
Requires-Dist: awscli (==1.27.89)
Requires-Dist: validators (==0.20.0)
Requires-Dist: aws-cdk-lib (==2.68.0)
Requires-Dist: constructs (==10.1.275)
